{
  "downloaded_in": "2023-05-28 15:40:21.395604-04:00",
  "url": "https://www.spiritfanfiction.com/historia/diario-de-aventuras-24890796",
  "title": "História Diário de AVENTURAS",
  "synopsis": "\nSinopse:\r\nNicolas vive várias aventuras com seus amigos Jonas, Caroline e Arthur, eles vão para um passeio surpresa, enfrentam os valentões do nono ano em um desafio escolar e fazem de tudo para não estragar as coisas, vêem cachorros de cores exóticas e coisas estranhas durante o caminho demorado dos passeios escolares.\r\n",
  "metadata": {
    "StartDate": "há 3 dias às 20:08",
    "LastUpdate": "17 minutos atrás",
    "Language": "Português",
    "Views": "4",
    "Stars": "1",
    "Comments": "1",
    "Listed": "0",
    "Words": "5.639",
    "Finished": "Sim",
    "Categories": "Histórias Originais",
    "Characters": "Originais",
    "Tags": "Aventura, Diário De Um Banana"
  },
  "chapter_urls": [
    "https://www.spiritfanfiction.com/historia/diario-de-aventuras-24890796/capitulos/24890799",
    "https://www.spiritfanfiction.com/historia/diario-de-aventuras-24890796/capitulos/24892724",
    "https://www.spiritfanfiction.com/historia/diario-de-aventuras-24890796/capitulos/24896579",
    "https://www.spiritfanfiction.com/historia/diario-de-aventuras-24890796/capitulos/24896843"
  ],
  "history": "Capítulo 1 - Uma nova semana\nDomingoHoje eu decidi que vou escrever nesse diário as coisas MALUCAS que acontecem comigo todo dia, hoje não tem aula por isso as coisas malucas são um pouco MELHORES ( eu acho ), mas durante a semana parece que todo o azar do mundo vai pra mim, mas acho que hoje isso não aconteceu, foi um dia normal exceto por UMA coisa: Hoje eu fui finalmente passear até o shopping, para chegar lá eu fui de carro, e fiquei olhando pela janela os cachorros que passeavam com seus donos na rua, até que apareceu um cachorro meio estranho, ele era azul e pequeno, eu olhei com uma cara de espanto e quando percebi estava de boca aberta.Continuando, quando entramos no estacionamento do shopping, não tinha NENHUM carro, só o nosso, então poderíamos escolher QUALQUER lugar para estacionar, então escolhemos o melhor lugar e fomos pro shopping, onde primeiro minha mãe quis ir a uma loja de roupas, e ficamos lá por uns 10 minutos, mais achei que já fazia MAIS de UMA HORA que estava lá.Logo depois fomos comer um lanche, eu quis pedir mais um mas minha mãe disse que não tinha mais dinheiro, e fomos para outra loja( o que achei muito estranho ) e ficamos indo em milhões de lojas literalmente IGUAIS por muito tempo, até que finalmente fomos à uma loja de brinquedos, era o que eu esperava desde o início, o único problema é que o brinquedo tinha que custar no MÁXIMO 30 reais, e os brinquedos lá eram todos de 200 reais para cima, e os únicos brinquedos BARATOS custavam uns 40 reais, isso complicou ainda mais, rodei a loja toda e nada, perguntei para minha mãe se ela podia AUMENTAR o valor mas a resposta você sabe, foi não. Pedi então para ir a uma outra loja, que ficava ao lado, os brinquedos eram mais baratos por lá ( pelomenos o que eu vi na vitrine ), então fomos, os brinquedos até que eram mais baratos, mas de PÉSSIMA qualidade, o que era ruim, tinha um carrinho bem maneiro, mas quando olhei direito ele estava sem rodas, como iria dar para brincar com eles usando a pista se ele não tem rodas para correr? Até que eu vi o brinquedo PERFEITO, tanto a qualidade quanto o PREÇO, era o boneco do novo jogo que havia lançado nessa semana, um jogo de astronautas, o boneco era de um dos alienígenas mais FORTES e MANEIROS do game, foi exatamente aquele que eu escolhi, minha mãe apenas disse que aquele boneco era horroroso.Segunda-feiraAgora que as coisas realmente iriam PIORAR, era segunda-feira, e era dia de passeio SURPRESA, iríamos até uma faculdade ver uns trabalhos e algumas aulas. Não sei como um passeio desse tipo pode ser realmente considerado um PASSEIO, já que normalmente os passeios são para as pessoas se divertirem e não fazer ou ver LIÇÕES. A professora estava irritada com aquele monte de conversa no ônibus, mesmo que ela tivesse dito que PODERÍAMOS CONVERSAR durante o caminho, ela estava com raiva pois não poderia reclamar já que ela disse que poderíamos conversar.Do meu lado estava sentado o Jonas, que era um dos meus melhores amigos junto com Caroline e Arthur. Jonas estava morrendo de sono e tentando dormir pois o passeio começou muito CEDO, mas era impossível dormir com o sol batendo na cara, já que ele sentou ao lado da janela.No banco ao lado tinham dois garotos comendo salgadinhos, eles estavam mastigando SUPER ALTO e eu realmente achei aquilo muito IRRITANTE, principalmente o Jonas, que estava tentando dormir.Teve uma hora que passamos próximos de uma rede de fast-food, onde queríamos ir no lugar do passeio, mas obviamente que não foi o que aconteceu. Todos ficaram gemendo empurrando levemente uns aos outros com cara de raivinha, todos irritados.A professora falou que se realmente fossemos para um fast-food seria um passeio PAGO, o que é muito injusto, tudo nesse mundo tem que PAGAR, menos passeios para FACULDADES, achei isso realmente ruim.Enquanto isso aqueles alunos do fundo do ônibus estavam quietos e desligados em tudo que tava acontecendo, era como se caísse um meteoro e eles tivessem ainda com fone de ouvido ouvindo músicas do século passado de olhos fechados. A professora precisava chamar a atenção deles a todo momento, senão eles ficariam para trás.Já faz uns 30 minutos que estamos TENTANDO chegar naquela faculdade, disseram que era bem perto mas eu não acho não, ou o ônibus que é LENTO ou o lugar que é LONGE, não sei, mas com certeza é um desses.Nem mais o que conversar nós tínhamos, ficávamos só encarando uns aos outros aleatoriamente para não dizer que não estamos fazendo NADA, mas tinha também as pessoas que estavam jogando joguinhos com o colega ao lado no celular, maa a maioria não estava fazendo absolutamente NADA além de se encarar.Aquilo estava ficando muito CHATO, até que a professora anunciou que havíamos chegado, todos levantaram num piscar de olhos dos bancos e correram para fora do ônibus, onde estava a professora esperando a fila ficar completa, mas tinha gente que NÃO queria ir, isso deixou a professora esperando por um tempo até um inspetor ir buscar o aluno.Aquela faculdade era muito diferente de qualquer outra que eu tenha visto na minha vida( embora eu NUNCA tenha visto uma faculdade ), ela tinha uns TRÊS andares, todos cada vez MENORES, nenhum do mesmo tamanho. As paredes totalmente azuis claro e escuro, janelas azuis claro, e o resto das paredes com partes brancas. A entrada com uma escada que já cansa só de olhar e um portão bem diferenciado LARANJA, acima um cartaz escrito \" BEM-VINDO A FACULDADE MAIS VISITADA DA CIDADE! \" Mas ainda não dizia o nome da faculdade, que era o que as pessoas pensariam descobrir lendo aquele pedaço de papel com uma impressão PÉSSIMA pendurado. Percebi que havia outro cartaz na escada, escrito \" Aberto para excursões escolares até o dia 23 de março \", então vi que a nossa escola realmente pega tudo de ÚLTIMA HORA, já que era dia 23, ou seja, o último dia para as excursões ocorrerem.A professora estava cansada de tanto subir degraus, pisar em pedras e quase pisar em algo pegajoso que havia no chão, enquanto eu pisei em milhares de cartazes que provavelmente foram arrancados no meio do caminho por certos estudantes. A entrada era até que BONITA, bem colorida, e um pátio imenso logo de cara, um corredor que provavelmente leva para salas de aulas e uma salinha pequena onde os funcionários guardam as coisas que são usadas por lá, como itens pros esportes, já que logo naquele amontoado de corredor estreito havia umas placas sinalizadoras mostrando onde ficava o corredor das quadras, haviam quadras de vôlei, basquete, futebol e uma espécie de futebol americano. Quando fomos jogar um pouco nas quadras, a professora nos deixou escolher entre basquete e futebol, a maioria foi no basquete, mas combinei com meus amigos para irmos no futebol, Jonas e Arthur eram goleiros e eu e Caroline éramos jogadores, aquilo mais parecia um jogo de dribles do que um jogo de futebol, mas não importava, era divertido do mesmo jeito, Jonas que era goleiro do meu time não conseguia pegar NENHUM gol que Caroline fazia, acho que eu deveria ter ficado no gol, enquanto Arthur pegava todos que eu TENTAVA fazer, era tipo um time PROFISSIONAL e outro PÉSSIMO.Continuamos o jogo até a professora aparecer e falar que iríamos a próxima parte do passeio, os trabalhos de ciências.Fomos no andar de cima onde fica o laboratório, estava cheio de plantas e suculentas, que provavelmente os alunos plantaram durante os trabalhos, tinham também trabalhos sobre o ESPAÇO, translação, rotação, revolução, Terra, Lua, Sol… e também os trabalhos sobre o corpo humano, esqueletos e outros tipos de esqueletos com órgãos de plástico para mostrar como nosso corpo funciona ( confesso que foi um pouco nojento ), mas, é claro que algo tinha que dar errado, um garoto chamado Lucas derrubou um dos esqueletos que estava cheio de órgãos de plástico, e depois ele teve de catar TUDO, e todo mundo tentando segurar o riso, e os que tinham levado celular começaram a tirar fotos e mandá-las para os pais e no grupo da escola, depois que Lucas pegou tudo e arrumou, fomos até a sala de ARTES, juro que não consigo chamar o que havia lá de ARTE, era um monte de RABISCOS aleatórios de cores diferentes com estrelas e outros desenhos desproporcionais, havia um pote com canetas de gel líquido e pincéis com várias tintas de várias cores bonitas ao lado e algumas tintas que foram aparentemente ignoradas por estarem misturadas.A professora deu uma folha para nós e falou para nós desenharmos planetas do sistema solar, eu desenhei Júpiter, já que ele tinha as cores que considerei mais BONITAS entre os materiais que tinha lá.O desenho ficou meio oval e torto, mas nem me importei e entreguei para a professora, ela tocou e acabou borrando pois a tinta ainda não estava seca. Jonas havia se sujado todo com a tinta que derramara no uniforme NOVO, e Alice borrou toda a mão, que ficou colorida.Após todos entregarem o desenho, fomos até a última sala( até que enfim ) me senti aliviado, era uma sala de culinária, tinha vários bolos, croissants, empadinhas, coxinhas e quibes, e o MELHOR DE TUDO, a professora nos DEIXOU comer o que quiséssemos, deu vontade de pular de tanta alegria, e olha que as pessoas cozinham muito BEM lá, já que tudo estava incrível.Eu peguei 2 de cada e comi rapidamente, já que nós já sairíamos logo dali e voltaríamos para o ônibus e voltar para casa, então na hora de voltar, nós pegamos uns lanchinhos e lembrancinhas e fomos até o ônibus, dessa vez tanto Jonas como eu conseguimos dormir, acordei com a professora dizendo \" Acorde Nicolas, já chegamos !\" Então em casa comi ainda mais lanches que eu trouxe do passeio, até que foi legal, muito MELHOR do que eu pensei que seria, e quando voltei em casa, lembrei que NADA de DESASTROSO havia acontecido comigo, um milagre?E também percebi agora que passei maior parte do livro apenas falando sobre um passeio curto.Terça-feiraHoje a aula seria sobre o passeio do dia anterior, e a galera que faltou ficou toda confusa e com raiva, afinal, como iriam saber sobre um PASSEIO SURPRESA? A professora entregou uma folha com 2 perguntas: 1)Qual foi a coisa que você mais gostou no passeio? [ Resposta Pessoal ]R:2) E qual foi a coisa que você menos gostou? [ Resposta Pessoal ]R:Eu respondi que o que mais gostei foi os lanches e o que menos gostei foi da desorganização do local, na hora de corrigir, a professora concordou com minha resposta.Izabela e Heitor foram os únicos que faltaram no dia do passeio, eles não receberam a folha e ficaram fazendo várias perguntas sobre o passeio para nós, não sei de onde eles tiraram TANTAS perguntas.A professora então disse que para nós \"descansarmos\" do passeio teríamos a aula TODA livre, eu peguei um jogo de cartas e fui jogar com meus amigos, tinhas uns também que levaram jogo da velha de madeira, não sei de onde eles desenterraram aquilo.De repente, chegou o VALENTÃO da sala, ele sempre chegava atrasado.Ele chegou e catou uma carta que estava no chão, que foi deixada pela turma da manhã, estava escrito:Aqui é a turma da manhã, e fizemos essa carta para desafiar vocês nos jogos escolares, se não forem medrosos e aceitarem, assinem abaixo e iremos destacar o papel e entregar para a professora de educação físicaAutorização de desafio dos nonos anos contra quintos anos( ) Sim( ) NãoNós resolvemos conversar sobre aceitar ou não, a professora olhou e disse que nós deveríamos aceitar, e disse que se a gente ganhasse, ganharíamos um prêmio, um PASSEIO GRÁTIS PARA A DISNEY!Rapidamente Jorge( o valentão ) aceitou o desafio, e deixamos a carta onde estava, e iríamos esperar uma resposta no outro dia.Quarta-feiraAo chegar na escola, Jorge foi até o local onde deixou a carta no dia anterior, lá estava outra carta, dizendo que no sábado a competição iria acontecer, disse que a Miriam( a diretora ) recebeu a autorização e que já teria marcado, e na carta deixaram uma lista que Miriam imprimiu de todos os desafios que teríamos de fazer:Futebol - Basquete - Vôlei - Corrida - Desenho - Parkour Nós apenas nos assustamos com a parte do parkour, somos HORRÍVEIS nisso, seria muito fácil para os caras do 9º ano vencerem, normalmente nós tropeçamos na hora de aterrissar no pulo, e isso já rendeu muitos problemas.Decidimos então que em todo esse tempo iríamos nos preparar para esse desafio, então no recreio que durava mais ou menos 50 minutos, treinamos muito o parkour nos bancos azuis colados na parede da escola, sentimos então que estávamos preparados.Na aula de educação física pedimos para o professor nos treinar, a professora de educação física conversou com ele sobre o desafio logo em seguida, o que deixou o professor duplamente motivado.  Capítulo 2 - A competição\nSábadoFinalmente, era o dia do DESAFIO, o professor de educação física nos treinos esses dias, sei que pulei vários dias do nada, mas é que eles foram muito sem graça e já basta saber que nós treinamos parkour e nos estropiamos muito.Quando cheguei, Jonas, Caroline, Jorge, Arthur, Alice, Magali, Felipe e Carla já estavam lá, enquanto ainda não tinha NINGUÉM do nono ano aqui, então nós pensamos que eles haviam DESISTIDO, o que era a coisa mais IMPROVÁVEL naquela hora, mas, mesmo assim, estava parecendo.Chamei o Jorge e perguntei onde estavam os caras do nono ano, ele respondeu — com uma voz furiosa — que eles disseram que se atrasariam um pouco, na mão de Jorge estava seu celular, aberto na conversa com Eduarda, que era a única do nono ano que ele tinha contato, onde ela dizia que eles demorariam um pouco para chegar e disse que não tinha tempo para explicar o PORQUÊ.De repente aquele barulho da porta abrindo foi ouvido, pensamos que era algum inspetor mas não, era finalmente o nono ano TODO chegando, logo já nos posicionamos, o primeiro desafio era FUTEBOL, e eu sou péssimo em futebol, mas Caroline e Arthur são os MELHORES, vou acreditar neles mesmo.Eles já começaram de um jeito bem louco, já começaram fazendo montinho em cima da bola, não é possível que um time TODO é FOMINHA, eles roubavam a bola um do outro, chutavam a canela do coleguinha… enfim, nós apenas ficamos olhando esperando eles se decidirem, até que finalmente, a bola saiu daquele meio e eu fui pegar, passei pro Arthur, ele levou a bola até o gol em ziguezague e chutou, a goleira encostou na bola, fazendo ela bater na trave, isso deu um pouco de raiva em Arthur, mas enfim, fazer o que? A goleira chutou a bola para um dos caras e ele foi dando um ziguezague bem louco até o nosso gol e chutou, só pensei o como eles são FOMINHA, e então, Caroline pegou a bola apenas com um chute, não deu nem tempo do goleiro pegar, Jorge estava na zaga, e tentou pegar a bola antes de Caroline, mas não conseguiu.QUE DROGA! Eu fiquei pensando quando o nosso goleiro chutou a bola para fazer um passe para Alice e acabou passando para uma menina do nono ano, ela chutou a bola e estava muito perto do gol, acabou que ela FEZ um gol, ela fez o famoso \"Siu\" com um GRITO e nós fizemos birra.O tempo estava acabando e nós estávamos PERDENDO, então eu pedi pro goleiro jogar para mim e fiquei bem longe de qualquer pessoa do nono ano, ele chutou para mim, andei um pouco dominando a bola e passei para Felipe, que fez ziguezague e passou para Caroline, que fez uma embaixada para receber o passe, chutou a bola pro gol e… QUASE! Foi por pouco que ela não fez um gol.Caroline ficou irritada.Bom, a goleira jogou a bola no MEIO do campo e chutei direto pro gol, acho que não fui muito inteligente, a bola caiu e um dos caras do nono ano dominou a bola e parou, acho que tava pensando em quem fazer passe, mas, nesse tempo, Carla pegou a bola e levou pro gol, onde fez um passe para Felipe, e… GOOOOOOOOL! Finalmente, e assim, o jogo terminou EMPATADO, o próximo desafio era BASQUETE, e o melhor, eu sou INCRÍVEL em basquete.Já fiquei feliz, era o melhor em basquete na escola TODA, e meus amigos eram ÓTIMOS também.Já comecei pegando a bola, já tentei jogar ela na cesta, mas não consegui. E ficou assim até o final, até que o jogo terminou 0 a 0.Eu só não narrei muito bem esse jogo de basquete, resolvi \"pular\" pois não sou um bom narrador de basquete, mas agora o próximo desafio é VÔLEI, eu sou muito bom em vôlei também, mas o nono ano é o dobro mais alto que nós, o que ajudou muito eles, mas nós nem ligamos.Então o jogo começou, eu joguei a bola pro alto e quando ela abaixou eu dei um TABEFÃO, a bola quase não passou pela rede, ou seja, passou de raspão, e com isso ela PERDEU velocidade, então o nono ano pegou a bola com FACILIDADE, isso é muito ruim, e então me preparei, era hora deles jogarem, então um deles pegou a bola, jogou para cima e começou a fazer tipo peteca até a bola pegar impulso, aí ele deu um tabefe e a bola saiu voando, eu quase deixei ESCORREGAR da minha mão, eu caí, mas peguei! Dei a bola agora para Caroline jogar, ela era nova no vôlei então dei para que ela tentasse pela PRIMEIRA vez, mas já que ela era MUITO boa, deu um tabefe monstro que fez a bola até dar um ziguezague no ar, e conseguimos nosso PRIMEIRO ponto, ESTÁVAMOS ganhando FINALMENTE! Uma menina do nono ano pegou a bola e começou a usar a mesma estratégia da peteca, e pegou um impulso imenso, que fez a bola até ROLAR, eu não consegui e deixei ela escorregar, empatou, 1 a 1. Mas ainda não tinha acabado, então eu peguei a bola e joguei com raiva, eles pegaram com facilidade, e na hora que ELES jogaram, a gente precisou fazer tipo um PARKOUR para pegar.E continuou indo dessa forma, joga dali, joga de lá, até que a gente jogou de um jeito PÉSSIMO raspando tudo, e isso funcionou como ESTRATÉGIA, e conseguimos mais um ponto, 2 a 1.Eles fizeram o MESMO que nós, parece que não tem criatividade… deram um tabefe raspando na bola, e nós quase não pegamos, tenho certeza de que se não tivesse alguém caído no meio do campo onde a bola foi não teríamos pego.De qualquer forma aquilo parecia ser SORTE e não HABILIDADE, e continuamos o jogo dando tabefes na pobre bola, até que o nono ano fez mais um PONTO, 2 a 2.O tempo estava quase acabando, tínhamos que desempatar logo aquele negócio, até que veio a oportunidade PERFEITA:Um dos caras do nono ano acabou machucando a mão e parou de jogar, e colocaram no lugar dele um reserva que não deixava NINGUÉM pegar ou jogar a bola, e ele era muito RUIM, então, jogamos a bola com esperança… ele pegou… e deixou CAIR! 3 a 2! VENCEMOS!Estávamos com 1 ponto nos desafios e o nono ano com ZERO pontos, o próximo desafio seria CORRIDA, não acho que sejamos mais rápidos que os caras do nono ano, mas fazer o quê?Agora seria dessa forma: primeiro nós iríamos correr, a professora iria contar o tempo que demorariamos para chegar ao final e somá-los, quem fizesse menos pontos ganharia.Comecei já até fazendo uma espécie de alongamento, até a professora começar: \"1, 2, 3!\" Eu corri mais rápido do pensei que iria CORRER, até dei um PULO, e consegui chegar em 2 minutos, nossa tabela foi feita e ficou assim:1 minuto e 54 segundos, 2 minutos e cinco segundos e 60 segundos ( um minuto )Somando tudo, ficamos com 1 2=3 1=4 • 54 5=59 • 4,59.Quase havia dado 5 minutos, mas conseguimos QUATRO, agora vamos ver o nono ano.Eles conseguiram 4 minutos EXATOS, e perdemos, estava então 1 a 1.O próximo desafio era desenho, e parkour logo depois.Felipe e Alice faziam um CURSO de desenho, isso iria AJUDAR muito o nosso time.O desafio era quem desenhava o melhor CARRO, confesso que tive que usar a tampinha da garrafa de água para fazer a roda CERTO, depois fiz um círculo torto dentro e fiz uma sombra bem ESTRANHA, o corpo do carro tinha que ficar bom, então peguei uma régua e fiz uma linha RETA, e fiz a parte da frente do carro, em baixo o traço era QUADRADO e em cima REDONDO, ficou até que bonito, fiz então o farol do carro e levantei o traço para fazer a parte de cima do carro, e assim completei o CONTORNO, ficou bom até.Para fazer as janelas fiz dois retângulos e fiz um traço do meio para ser a PORTA, e um risquinho para ser aquele negócio que usam para abrir a porta.Assim estava PRONTO, peguei um lápis bem PROFISSIONAL e fiz uma sombra, depois passei o dedo. Para finalizar era hora do contorno: peguei uma canetinha de ponta fina e consegui fazer sem erro algum, o que já era um MILAGRE.Entreguei a professora que deu um OITO, ela disse que a sombra tinha ficado muito sem sentido ao cenário que eu fiz( um monte de árvores tortas e uma rua desproporcional)Fiquei olhando os outros receberem as notas, todos receberam um nove, pelo menos não era um nota RUIM, mas para o desafio, poderia ser.O nono ano fez uns garranchos TERRÍVEIS, tiraram 3, mas se fosse eu com toda certeza daria um ZERO.dessa vez nós GANHAMOS, 2 a 1.Agora, seria o PIOR, era hora do desafio de parkour, fomos até o quintal da quadra e vimos uma plataforma maluca, quem conseguisse passar ganharia e finalizaria TUDO, tínhamos que vencer ou o desafio terminaria EMPATADO.Fomos indo bem devagar, aproveitando que não tinha esse negócio de tempo e finalmente poderíamos fazer as coisas com CALMA.Até que TROPEÇAMOS e, por pouco, Arthur não tropeçou, ele continuou, e… faltava UMA plataforma, estava muito longe e precisaria de um pulo diferente para passar, ele parou, foi para trás até a borda, pegou impulso e pulou. PASSOU! Nós vencemos!Começamos a pular de alegria, vencemos o desafio e receberíamos o prêmio do passeio que foi marcado para segunda.Capítulo 3 - Passeio\nDomingoAgora já é a segunda semana que estou escrevendo esse livro, e sinto que não está sendo o que eu queria, já que não vem acontecendo nada de DESASTROSO comigo, e sim, pode parecer estranho mas isso está sendo RUIM para mim, só por que agora quero tirar PROVEITO disso, isso para.Bom, hoje meu tio RICO veio me visitar, ele trouxe para mim um videogame novo, com um controle vermelho IRADO, já quis logo usar, fiquei jogando com os meus amigos a tarde toda enquanto meus pais conversavam sobre uma VIAGEM que iríamos fazer com meu tio, já que eles tiveram que remarcar para a terça por causa do meu passeio escolar, afinal, meus pais queriam que eu celebrasse minha vitória nos jogos escolares, e eu fiquei feliz pois aí seriam DOIS passeios para mim. Peguei o celular e comecei a falar com a galera no grupo de celular, começamos a comentar sobre o PASSEIO, nós não sabíamos que parque aquático SERIA, só sabíamos que era um parque aquático e mais NADA, então decidimos tentar mandar um email pra professora perguntando, já que sabíamos o email dela pelo aplicativo da escola, mandamos e começamos a esperar, passaram-se aproximadamente 10 minutos e ela mandou uma resposta, ela disse que seria o parque aquático Water & Fun, o parque aquático mais IRADO do momento, quando a notícia se espalhou todos PULARAM de alegria, FINALMENTE um passeio que preste nisso, até achamos estranho.A professora deu VÁRIOS detalhes sobre o passeio, o email ficou mais ou menos assim:O passeio será no parque aquático Water & Fun, pois conseguimos uma boa promoção para passeios escolares, no passeio já recebemos a autorização das mães de todos antes dos jogos escolares, vocês comerão hambúrguer e terão todas as áreas do local para se divertirem, como só teriam vocês e mais ninguém e várias pessoas do parque estarão espalhadas e vocês podem ir onde quiserem, só isso para falar.Professora Fábia.Gostei da parte do hambúrguer e que poderíamos ir onde a gente quisesse.Meu tio iria ficar na minha casa até TERÇA, no dia em que iríamos passear, então poderia pedir um monte de coisa para ele, pedi para ele me dar uns BRINQUEDOS, ele rapidamente disse que sim, ele sempre me mimou a vida INTEIRA, então, obviamente ele iria comprar os brinquedos, voltei da loja com um MONTE de sacolas CHEIAS de brinquedos, foi o melhor dia de todos.Segunda-feiraFinalmente era o dia do passeio, entrei na escola já vendo que cheguei meio que ATRASADO, mas não me incomodei muito com isso, já que pelo menos não cheguei tão tarde a ponto de PERDER o passeio, só me sentei no auditório e olhei para as professoras, conferindo se todos já haviam chegado.Até que finalmente a professora nos chamou para irmos até o ônibus, eu estava tão ANSIOSO que meus dentes estão RANGENDO, mas logo pararam quando sentei no banco confortável do ônibus, inclinei a cadeira e fiquei \"deitado\", acabou que NINGUÉM sentou do meu lado, eu achei isso até que BOM, porque pelo menos assim ninguém iria me incomodar.O ônibus começou a andar e eu peguei um livro que coloquei na minha mochila, comecei a ler para me distrair, só que as BATIDAS do ônibus andando estavam atrapalhando tudo, tentei pegar meu fone de ouvido mas não era o som e sim a vibração, tentei me acostumar, e depois de um tempo eu consegui, então comecei a ler meu livro, eu estava na página 10 e o livro tinha 2090 PÁGINAS, sei que é muito mas até que é legal esses livros compridos, pois tem muito conteúdo.Na primeira hora que paramos no farol vermelho, meio que eu desacostumei das batidas, e tive que ir acostumando e reacostumando  a cada parada.Já estávamos próximos do parque aquático, o Water & Fun é um parque aquático que foi inaugurado esse ano, então ninguém sabe muito sobre ele, já que quase NINGUÉM foi lá.Levei o livro para escrever no ônibus, então realmente não sei o que vai acontecer depois diferentemente de todas as outras coisas que contei aqui, achei que dessa forma seria mais LEGAL, mas acho que isso também faz minha criatividade acabar TOTALMENTE.A professora chamou para descermos do ônibus, havíamos chegado, às ruas estavam muito vazias e o parque TAMBÉM, lá só haviam monitores que iriam ficar rodeando o parque todo para nossa SEGURANÇA, a professora falou que na hora de comer ela nos chamaria por um relógio que ela nos deu e falou para irmos nos espalhar e brincar.Eu fui direto pro tobogã mais próximo, desci RAPIDAMENTE e já fui correndo denovo, até que de longe, vi um bem mais alto, e fui indo em vários até chegar no MAIS ALTO, ele tinha até CURVAS, eu confesso que fiquei com um pouco de medo, fui e AMEI, continuei indo sem parar.O tempo estava passando e eu nem percebi, até que finalmente chegou a hora de ir comer, comi e agora deu uma pausa para escrever o livro, vou deixar o livro aqui e voltar.Bom, eu fui até outros tipos de atrações do parque, não fui SÓ em tobogãs, fui em piscinas e em uns escorregadores e balanços do mini-parque que havia no canto, saí de lá coberto de areia, todo mundo veio me perguntar onde estava o parquinho que eu fui. O tempo foi passando até que começou a ESCURECER e foi aí que as coisas ficaram ESTRANHAS.Nós fomos brincar em um tobogã, todos juntos, e quando saímos do tobogã, vimos que cada vez escurecia MAIS ainda, só que era MUITO rápido, chegava a ser estranho, até que percebemos que iria CHOVER.Saímos correndo todos pro ônibus, nosso passeio foi interrompido, mas mesmo assim nós gostamos do passeio e conseguimos aproveitar BASTANTE, a saída foi muito engraçada, pois agora estava tudo escuro e com um cheiro de chuva, aí ouvimos um trovão e o toró COMEÇOU.Estava chovendo muito forte, também estava caindo raios e agora sim, todo o azar veio para nós, ficamos até com medo de um raio cair no ônibus.Quando chegamos em casa, depois de passar da escola e tudo, começamos a conversar sobre o passeio, até que meu tio entrou no quarto e disse que no dia seguinte iríamos para a PRAIA, na casa de praia dele.Concordei com a cabeça, ele fechou um pouco a porta e disse que era hora de dormir, fechou a porta e foi pra sala, então eu fui dormir, nem sabia que era tão tarde assim.Notas Finais\nEsse livro é um livro inspirado em diário de um banana, ou seja, um tipo de livro em que o personagem principal escreve um diário ou livro de memórias com momentos legais e engraçados no livro, e como todos eles, o primeiro tem apenas o nome oficial do livro, mas os próximos terão um nome.Diário de AVENTURAS"
}